tableaudocumentapi/__init__.py
tableaudocumentapi/connection.py
tableaudocumentapi/datasource.py
tableaudocumentapi/dbclass.py
tableaudocumentapi/field.py
tableaudocumentapi/multilookup_dict.py
tableaudocumentapi/property_decorators.py
tableaudocumentapi/workbook.py
tableaudocumentapi/xfile.py
alt_tableaudocumentapi-0.8.dist-info/LICENSE
alt_tableaudocumentapi-0.8.dist-info/METADATA
alt_tableaudocumentapi-0.8.dist-info/WHEEL
alt_tableaudocumentapi-0.8.dist-info/top_level.txt
alt_tableaudocumentapi-0.8.dist-info/RECORD
