Metadata-Version: 2.1
Name: alt_tableaudocumentapi
Version: 0.8
Summary: An alternative Python module for working with Tableau files.
Home-page: https://github.com/dev-mkc19/document-api-python
Author: Mikhail Korotchenkov
Author-email: mr.mkc19@hotmail.com
License: MIT
Platform: UNKNOWN
License-File: LICENSE
